pyterprise/__init__.py
pyterprise/_api_response_object.py
pyterprise/client.py
pyterprise/exceptions.py
pyterprise/handler.py
pyterprise/organization.py
pyterprise/run.py
pyterprise/ssh_key.py
pyterprise/variable.py
pyterprise/workspace.py
pyterprise-0.0.15.dist-info/METADATA
pyterprise-0.0.15.dist-info/WHEEL
pyterprise-0.0.15.dist-info/top_level.txt
pyterprise-0.0.15.dist-info/RECORD
