Metadata-Version: 2.1
Name: pyterprise
Version: 0.0.15
Summary: A small client library for the Terraform Enterprise REST API.
Home-page: https://github.com/Fotherbyy/PyTerprise
Author: James Fotherby
Author-email: fotherby1@gmail.com
License: UNKNOWN
Platform: UNKNOWN
Classifier: Programming Language :: Python :: 3
Classifier: License :: OSI Approved :: MIT License
Classifier: Operating System :: OS Independent
Requires-Dist: requests
